webson/__init__.py
webson/_const.py
webson/_functions.py
webson/_types.py
webson/_webson.py
webson/py.typed
webson-0.1.6.dist-info/METADATA
webson-0.1.6.dist-info/WHEEL
webson-0.1.6.dist-info/entry_points.txt
webson-0.1.6.dist-info/licenses/LICENSE
webson-0.1.6.dist-info/RECORD
