Metadata-Version: 2.4
Name: webson
Version: 0.1.6
Summary: Turn any webpage into structured outputs!
Author-email: Arthur Brenno <64020210+arthurbrenno@users.noreply.github.com>
License-File: LICENSE
Requires-Python: >=3.13
Requires-Dist: architecture>=0.5.44
Requires-Dist: intellibricks>=0.7.24
Requires-Dist: markdownify>=0.14.1
Requires-Dist: msgspec>=0.19.0
Requires-Dist: playwright>=1.49.1
Requires-Dist: requests>=2.32.3
